auto_argparse/__init__.py
auto_argparse/auto_argparse.py
auto_argparse-0.0.8.dist-info/LICENSE
auto_argparse-0.0.8.dist-info/METADATA
auto_argparse-0.0.8.dist-info/WHEEL
auto_argparse-0.0.8.dist-info/top_level.txt
auto_argparse-0.0.8.dist-info/RECORD
