Metadata-Version: 2.1
Name: auto-argparse
Version: 0.0.8
Summary: Automatically create argparse parsers.
Home-page: https://github.com/neighthan/auto-argparse
Author: Nathan Hunt
Author-email: neighthan.hunt@gmail.com
License: MIT
Platform: UNKNOWN
